dxc/__init__.py
dxc/ai/__init__.py
dxc/ai/AI_guild/AI_guild.py
dxc/ai/AI_guild/__init__.py
dxc/ai/clean_data/__init__.py
dxc/ai/clean_data/clean_data.py
dxc/ai/datasets/__init__.py
dxc/ai/datasets/_base.py
dxc/ai/datasets/data/.DS_Store
dxc/ai/datasets/data/ab_nyc_2019.csv
dxc/ai/datasets/data/ab_nyc_2019.txt
dxc/ai/datasets/data/abalone.csv
dxc/ai/datasets/data/abalone.txt
dxc/ai/datasets/data/abdata.csv
dxc/ai/datasets/data/auto_imports.csv
dxc/ai/datasets/data/auto_imports.txt
dxc/ai/datasets/data/bike_sharing_data.csv
dxc/ai/datasets/data/bike_sharing_data.txt
dxc/ai/datasets/data/breast_cancer.csv
dxc/ai/datasets/data/breast_cancer.txt
dxc/ai/datasets/data/breast_cancer_wisconsin.csv
dxc/ai/datasets/data/breast_cancer_wisconsin.txt
dxc/ai/datasets/data/german.csv
dxc/ai/datasets/data/german.txt
dxc/ai/datasets/data/hand_written_digits.csv
dxc/ai/datasets/data/hand_written_digits.txt
dxc/ai/datasets/data/horse_colic.csv
dxc/ai/datasets/data/horse_colic.txt
dxc/ai/datasets/data/house_prices.csv
dxc/ai/datasets/data/house_prices.txt
dxc/ai/datasets/data/housing.csv
dxc/ai/datasets/data/housing.txt
dxc/ai/datasets/data/hr_employee_attrition.csv
dxc/ai/datasets/data/hr_employee_attrition.txt
dxc/ai/datasets/data/ionosphere.csv
dxc/ai/datasets/data/ionosphere.txt
dxc/ai/datasets/data/iris.csv
dxc/ai/datasets/data/iris.txt
dxc/ai/datasets/data/oil_spill.csv
dxc/ai/datasets/data/oil_spill.txt
dxc/ai/datasets/data/pima_indians_diabetes.csv
dxc/ai/datasets/data/pima_indians_diabetes.txt
dxc/ai/datasets/data/sonar.csv
dxc/ai/datasets/data/sonar.txt
dxc/ai/datasets/data/wheat_seeds.csv
dxc/ai/datasets/data/wheat_seeds.txt
dxc/ai/datasets/data/winequality_red.csv
dxc/ai/datasets/data/winequality_red.txt
dxc/ai/datasets/data/winequality_white.csv
dxc/ai/datasets/data/winequality_white.txt
dxc/ai/deep_learning/__init__.py
dxc/ai/deep_learning/image_classifier.py
dxc/ai/define_layers/__init__.py
dxc/ai/define_layers/define_layers.py
dxc/ai/define_memory/__init__.py
DXC_RL-1.0.3.5.dist-info/LICENSE
DXC_RL-1.0.3.5.dist-info/METADATA
DXC_RL-1.0.3.5.dist-info/WHEEL
DXC_RL-1.0.3.5.dist-info/entry_points.txt
DXC_RL-1.0.3.5.dist-info/top_level.txt
DXC_RL-1.0.3.5.dist-info/RECORD
