Metadata-Version: 2.1
Name: DXC-RL
Version: 1.0.3.5
Summary: Python library which is extensively used for all AI projects
Home-page: https://github.com/SureshAthanti/DXC-Industrialized-AI-Starter
Author: DXC
License: Apache License 2.0
Platform: any
Classifier: License :: OSI Approved :: Apache Software License
Classifier: Programming Language :: Python :: 3.7
Requires-Dist: JIRA
Requires-Dist: scikit-learn (==0.22.2.post1)
Requires-Dist: auto-ml
Requires-Dist: Algorithmia
Requires-Dist: gitpython
Requires-Dist: flatten-json (==0.1.7)
Requires-Dist: pyjanitor
Requires-Dist: ftfy
Requires-Dist: arrow
Requires-Dist: pandas-profiling[notebook] (==2.9.0)
Requires-Dist: scrubadub
Requires-Dist: yellowbrick (==1.1)
Requires-Dist: datacleaner
Requires-Dist: missingno
Requires-Dist: pymongo
Requires-Dist: IPython
Requires-Dist: dnspython
Requires-Dist: pmdarima
Requires-Dist: pyaf
Requires-Dist: interpret-community
Requires-Dist: flask-cors
Requires-Dist: gevent
Requires-Dist: tpot
Requires-Dist: gym
Requires-Dist: keras-rl2
Requires-Dist: tensorflow
